GolangShixianWangluoPachong/README.md
GolangShixianWangluoPachong/__init__.py
GolangShixianWangluoPachong/__main__.py
GolangShixianWangluoPachong/file.epub
GolangShixianWangluoPachong/index.html
GolangShixianWangluoPachong/css/__init__.py
GolangShixianWangluoPachong/css/annotations.css
GolangShixianWangluoPachong/css/main.css
GolangShixianWangluoPachong/css/normalize.css
GolangShixianWangluoPachong/css/popup.css
GolangShixianWangluoPachong/font/__init__.py
GolangShixianWangluoPachong/font/fontello.eot
GolangShixianWangluoPachong/font/fontello.svg
GolangShixianWangluoPachong/font/fontello.ttf
GolangShixianWangluoPachong/font/fontello.woff
GolangShixianWangluoPachong/img/__init__.py
GolangShixianWangluoPachong/img/annotator-glyph-sprite.png
GolangShixianWangluoPachong/img/annotator-icon-sprite.png
GolangShixianWangluoPachong/img/apple-touch-icon.png
GolangShixianWangluoPachong/img/cancelfullscreen.png
GolangShixianWangluoPachong/img/close.png
GolangShixianWangluoPachong/img/fullscreen.png
GolangShixianWangluoPachong/img/loader.gif
GolangShixianWangluoPachong/img/menu-icon.png
GolangShixianWangluoPachong/img/save.png
GolangShixianWangluoPachong/img/saved.png
GolangShixianWangluoPachong/img/settings-s.png
GolangShixianWangluoPachong/img/settings.png
GolangShixianWangluoPachong/img/star.png
GolangShixianWangluoPachong/js/__init__.py
GolangShixianWangluoPachong/js/epub.js
GolangShixianWangluoPachong/js/epub.min.js
GolangShixianWangluoPachong/js/epub.min.map
GolangShixianWangluoPachong/js/hooks.min.js
GolangShixianWangluoPachong/js/hooks.min.map
GolangShixianWangluoPachong/js/reader.js
GolangShixianWangluoPachong/js/reader.js.map
GolangShixianWangluoPachong/js/reader.min.js
GolangShixianWangluoPachong/js/reader.min.map
GolangShixianWangluoPachong/js/hooks/__init__.py
GolangShixianWangluoPachong/js/hooks/extensions/__init__.py
GolangShixianWangluoPachong/js/hooks/extensions/highlight.js
GolangShixianWangluoPachong/js/libs/__init__.py
golang_shixian_wangluo_pachong-2024.3.5.0.dist-info/METADATA
golang_shixian_wangluo_pachong-2024.3.5.0.dist-info/WHEEL
golang_shixian_wangluo_pachong-2024.3.5.0.dist-info/entry_points.txt
golang_shixian_wangluo_pachong-2024.3.5.0.dist-info/top_level.txt
golang_shixian_wangluo_pachong-2024.3.5.0.dist-info/RECORD
